<?xml version="1.0" encoding="utf-8" ?><dwsync><file name="block-superfish.tpl.php" server="psurh.com" local="3403007366" remote="11996502546" /><file name="block.tpl.php" server="psurh.com" local="3403007366" remote="11996502546" /><file name="book-navigation.tpl.php" server="psurh.com" local="3403007366" remote="11996502547" /><file name="chamfer.info" server="psurh.com" local="3403007366" remote="11996502547" /><file name="comment.tpl.php" server="psurh.com" local="3403007366" remote="11996502547" /><file name="header.png" server="psurh.com" local="3403007366" remote="11996502555" /><file name="jquery_colorpicker.js" server="psurh.com" local="3403007366" remote="11996502559" /><file name="LICENSE.txt" server="psurh.com" local="3403007366" remote="11996502562" /><file name="logo.png" server="psurh.com" local="3403007366" remote="11996502562" /><file name="node.tpl.php" server="psurh.com" local="3403007366" remote="11996502562" /><file name="page.tpl.php" server="psurh.com" local="3403007366" remote="11996502562" /><file name="README.txt" server="psurh.com" local="3403007366" remote="11996502563" /><file name="screenshot.png" server="psurh.com" local="3403007366" remote="11996502563" /><file name="settings.js" server="psurh.com" local="3403007366" remote="11996502563" /><file name="slide-player.css" server="psurh.com" local="3403007366" remote="11996502563" /><file name="sticky_footer.css" server="psurh.com" local="3403007366" remote="11996502564" /><file name="style.css" server="psurh.com" local="3403007366" remote="11996502564" /><file name="template.php" server="psurh.com" local="3403007366" remote="11996502572" /><file name="theme-settings.php" server="psurh.com" local="3403007366" remote="11996502572" /></dwsync>