<?xml version="1.0" encoding="utf-8" ?><dwsync><file name="imce.admin.inc" server="online.aanda.psu.edu:1855//var/www/html/" local="3401209519" remote="11995353259" /><file name="imce.core.profiles.inc" server="online.aanda.psu.edu:1855//var/www/html/" local="3401209519" remote="11995353259" /><file name="imce.js.inc" server="online.aanda.psu.edu:1855//var/www/html/" local="3401209519" remote="11995353259" /><file name="imce.page.inc" server="online.aanda.psu.edu:1855//var/www/html/" local="3401209519" remote="11995353259" /><file name="imce.admin.inc" server="onlineaa.vmhost.psu.edu:1855//var/www/html/" local="3401209519" remote="11998468713" /><file name="imce.core.profiles.inc" server="onlineaa.vmhost.psu.edu:1855//var/www/html/" local="3401209519" remote="11998468713" /><file name="imce.js.inc" server="onlineaa.vmhost.psu.edu:1855//var/www/html/" local="3401209519" remote="11998468713" /><file name="imce.page.inc" server="onlineaa.vmhost.psu.edu:1855//var/www/html/" local="3401209519" remote="11998468713" /></dwsync>