<?xml version="1.0" encoding="utf-8" ?><dwsync><file name="allElements.css" server="elms.psu.edu:1855//var/www/html/" local="3384109542" remote="11997104573" /><file name="allElements.html" server="elms.psu.edu:1855//var/www/html/" local="3384109542" remote="11997104573" /><file name="legacy.css" server="elms.psu.edu:1855//var/www/html/" local="3384109542" remote="11997104573" /><file name="legacy.html" server="elms.psu.edu:1855//var/www/html/" local="3384109542" remote="11997104573" /><file name="allElements.css" server="onlineaa.vmhost.psu.edu:1855//var/www/html/" local="3384109542" remote="11998483399" /><file name="allElements.html" server="onlineaa.vmhost.psu.edu:1855//var/www/html/" local="3384109542" remote="11998483399" /><file name="legacy.css" server="onlineaa.vmhost.psu.edu:1855//var/www/html/" local="3384109542" remote="11998483399" /><file name="legacy.html" server="onlineaa.vmhost.psu.edu:1855//var/www/html/" local="3384109542" remote="11998483399" /></dwsync>