<?xml version="1.0" encoding="utf-8" ?><dwsync><file name="advanced_help.de.po" server="online.aanda.psu.edu:1855//var/www/html/" local="3403007366" remote="11995352996" /><file name="advanced_help.hu.po" server="online.aanda.psu.edu:1855//var/www/html/" local="3403007366" remote="11995352996" /><file name="advanced_help.pot" server="online.aanda.psu.edu:1855//var/www/html/" local="3403007366" remote="11995352996" /><file name="fr.po" server="online.aanda.psu.edu:1855//var/www/html/" local="3403007366" remote="11995352996" /><file name="advanced_help.de.po" server="onlineaa.vmhost.psu.edu:1855//var/www/html/" local="3403007366" remote="11998468617" /><file name="advanced_help.hu.po" server="onlineaa.vmhost.psu.edu:1855//var/www/html/" local="3403007366" remote="11998468617" /><file name="advanced_help.pot" server="onlineaa.vmhost.psu.edu:1855//var/www/html/" local="3403007366" remote="11998468617" /><file name="fr.po" server="onlineaa.vmhost.psu.edu:1855//var/www/html/" local="3403007366" remote="11998468617" /></dwsync>