<?xml version="1.0" encoding="utf-8" ?><dwsync><file name="blank.gif" server="online.aanda.psu.edu:1855//var/www/html/" local="3403007366" remote="11995353286" /><file name="brokenimage.jpg" server="online.aanda.psu.edu:1855//var/www/html/" local="3403007366" remote="11995353286" /><file name="close.gif" server="online.aanda.psu.edu:1855//var/www/html/" local="3403007366" remote="11995353286" /><file name="close_hover.gif" server="online.aanda.psu.edu:1855//var/www/html/" local="3403007366" remote="11995353286" /><file name="close_hover.gif.png" server="online.aanda.psu.edu:1855//var/www/html/" local="3403007366" remote="11995353286" /><file name="close_lite.gif" server="online.aanda.psu.edu:1855//var/www/html/" local="3403007366" remote="11995353286" /><file name="closelabel.gif" server="online.aanda.psu.edu:1855//var/www/html/" local="3403007366" remote="11995353286" /><file name="closelabel.gif.png" server="online.aanda.psu.edu:1855//var/www/html/" local="3403007366" remote="11995353287" /><file name="contract.gif" server="online.aanda.psu.edu:1855//var/www/html/" local="3403007366" remote="11995353287" /><file name="expand.gif" server="online.aanda.psu.edu:1855//var/www/html/" local="3403007366" remote="11995353287" /><file name="loading.gif" server="online.aanda.psu.edu:1855//var/www/html/" local="3403007366" remote="11995353287" /><file name="loading_lite.gif" server="online.aanda.psu.edu:1855//var/www/html/" local="3403007366" remote="11995353287" /><file name="next.gif" server="online.aanda.psu.edu:1855//var/www/html/" local="3403007366" remote="11995353287" /><file name="next_alt.gif" server="online.aanda.psu.edu:1855//var/www/html/" local="3403007366" remote="11995353287" /><file name="next_hover.gif" server="online.aanda.psu.edu:1855//var/www/html/" local="3403007366" remote="11995353287" /><file name="nextlabel.gif" server="online.aanda.psu.edu:1855//var/www/html/" local="3403007366" remote="11995353287" /><file name="nextlabel.gif.png" server="online.aanda.psu.edu:1855//var/www/html/" local="3403007366" remote="11995353287" /><file name="overlay.png" server="online.aanda.psu.edu:1855//var/www/html/" local="3403007366" remote="11995353287" /><file name="pause.png" server="online.aanda.psu.edu:1855//var/www/html/" local="3403007366" remote="11995353287" /><file name="play.png" server="online.aanda.psu.edu:1855//var/www/html/" local="3403007366" remote="11995353287" /><file name="prev.gif" server="online.aanda.psu.edu:1855//var/www/html/" local="3403007366" remote="11995353287" /><file name="prev_alt.gif" server="online.aanda.psu.edu:1855//var/www/html/" local="3403007366" remote="11995353287" /><file name="prev_hover.gif" server="online.aanda.psu.edu:1855//var/www/html/" local="3403007366" remote="11995353287" /><file name="prevlabel.gif" server="online.aanda.psu.edu:1855//var/www/html/" local="3403007366" remote="11995353287" /><file name="prevlabel.gif.png" server="online.aanda.psu.edu:1855//var/www/html/" local="3403007366" remote="11995353287" /><file name="blank.gif" server="onlineaa.vmhost.psu.edu:1855//var/www/html/" local="3403007366" remote="11998468744" /><file name="brokenimage.jpg" server="onlineaa.vmhost.psu.edu:1855//var/www/html/" local="3403007366" remote="11998468744" /><file name="close.gif" server="onlineaa.vmhost.psu.edu:1855//var/www/html/" local="3403007366" remote="11998468744" /><file name="close_hover.gif" server="onlineaa.vmhost.psu.edu:1855//var/www/html/" local="3403007366" remote="11998468744" /><file name="close_hover.gif.png" server="onlineaa.vmhost.psu.edu:1855//var/www/html/" local="3403007366" remote="11998468744" /><file name="close_lite.gif" server="onlineaa.vmhost.psu.edu:1855//var/www/html/" local="3403007366" remote="11998468744" /><file name="closelabel.gif" server="onlineaa.vmhost.psu.edu:1855//var/www/html/" local="3403007366" remote="11998468744" /><file name="closelabel.gif.png" server="onlineaa.vmhost.psu.edu:1855//var/www/html/" local="3403007366" remote="11998468744" /><file name="contract.gif" server="onlineaa.vmhost.psu.edu:1855//var/www/html/" local="3403007366" remote="11998468744" /><file name="expand.gif" server="onlineaa.vmhost.psu.edu:1855//var/www/html/" local="3403007366" remote="11998468744" /><file name="loading.gif" server="onlineaa.vmhost.psu.edu:1855//var/www/html/" local="3403007366" remote="11998468744" /><file name="loading_lite.gif" server="onlineaa.vmhost.psu.edu:1855//var/www/html/" local="3403007366" remote="11998468746" /><file name="next.gif" server="onlineaa.vmhost.psu.edu:1855//var/www/html/" local="3403007366" remote="11998468746" /><file name="next_alt.gif" server="onlineaa.vmhost.psu.edu:1855//var/www/html/" local="3403007366" remote="11998468746" /><file name="next_hover.gif" server="onlineaa.vmhost.psu.edu:1855//var/www/html/" local="3403007366" remote="11998468746" /><file name="nextlabel.gif" server="onlineaa.vmhost.psu.edu:1855//var/www/html/" local="3403007366" remote="11998468746" /><file name="nextlabel.gif.png" server="onlineaa.vmhost.psu.edu:1855//var/www/html/" local="3403007366" remote="11998468746" /><file name="overlay.png" server="onlineaa.vmhost.psu.edu:1855//var/www/html/" local="3403007366" remote="11998468746" /><file name="pause.png" server="onlineaa.vmhost.psu.edu:1855//var/www/html/" local="3403007366" remote="11998468746" /><file name="play.png" server="onlineaa.vmhost.psu.edu:1855//var/www/html/" local="3403007366" remote="11998468746" /><file name="prev.gif" server="onlineaa.vmhost.psu.edu:1855//var/www/html/" local="3403007366" remote="11998468746" /><file name="prev_alt.gif" server="onlineaa.vmhost.psu.edu:1855//var/www/html/" local="3403007366" remote="11998468746" /><file name="prev_hover.gif" server="onlineaa.vmhost.psu.edu:1855//var/www/html/" local="3403007366" remote="11998468746" /><file name="prevlabel.gif" server="onlineaa.vmhost.psu.edu:1855//var/www/html/" local="3403007366" remote="11998468746" /><file name="prevlabel.gif.png" server="onlineaa.vmhost.psu.edu:1855//var/www/html/" local="3403007366" remote="11998468746" /></dwsync>