<?xml version="1.0" encoding="utf-8" ?><dwsync><file name="LICENSE.txt" server="online.aanda.psu.edu:1855//var/www/html/" local="3403007366" remote="11995353293" /><file name="nodereference_url.info" server="online.aanda.psu.edu:1855//var/www/html/" local="3403007366" remote="11995353293" /><file name="nodereference_url.install" server="online.aanda.psu.edu:1855//var/www/html/" local="3403007366" remote="11995353293" /><file name="nodereference_url.module" server="online.aanda.psu.edu:1855//var/www/html/" local="3403007366" remote="11995353293" /><file name="README.txt" server="online.aanda.psu.edu:1855//var/www/html/" local="3403007366" remote="11995353293" /><file name="LICENSE.txt" server="onlineaa.vmhost.psu.edu:1855//var/www/html/" local="3403007366" remote="11998468755" /><file name="nodereference_url.info" server="onlineaa.vmhost.psu.edu:1855//var/www/html/" local="3403007366" remote="11998468755" /><file name="nodereference_url.install" server="onlineaa.vmhost.psu.edu:1855//var/www/html/" local="3403007366" remote="11998468755" /><file name="nodereference_url.module" server="onlineaa.vmhost.psu.edu:1855//var/www/html/" local="3403007366" remote="11998468755" /><file name="README.txt" server="onlineaa.vmhost.psu.edu:1855//var/www/html/" local="3403007366" remote="11998468755" /></dwsync>